<?xml version="1.0" encoding="utf-8"?>
<!DOCTYPE hibernate-mapping PUBLIC "-//Hibernate/Hibernate Mapping DTD 3.0//EN"
"http://www.hibernate.org/dtd/hibernate-mapping-3.0.dtd">
<!-- 
    Mapping file autogenerated by MyEclipse Persistence Tools
-->
<hibernate-mapping>
    <class name="edu.etju.model.Student" table="student" catalog="learningmy">
        <id name="aid" type="java.lang.Integer">
            <column name="aid" />
            <generator class="assigned" />
        </id>
        <many-to-one name="classmemeber" class="edu.etju.model.Classmemeber" fetch="select">
            <column name="cid" length="10" />
        </many-to-one>
        <property name="sid" type="java.lang.String">
            <column name="sid" length="15" />
        </property>
        <property name="susername" type="java.lang.String">
            <column name="susername" length="16" />
        </property>
        <property name="spassword" type="java.lang.String">
            <column name="spassword" length="26" />
        </property>
        <property name="icon" type="java.lang.String">
            <column name="icon" length="80" />
        </property>
        <property name="saname" type="java.lang.String">
            <column name="saname" length="10" />
        </property>
        <property name="school" type="java.lang.String">
            <column name="school" length="25" />
        </property>
        <property name="college" type="java.lang.String">
            <column name="college" length="20" />
        </property>
        <property name="icard" type="java.lang.String">
            <column name="icard" length="20" />
        </property>
    </class>
</hibernate-mapping>
